novana/__init__.py
novana/api.py
novana/chem.py
novana/core.py
novana/enumerate.py
novana/exception.py
novana/process.py
novana/utils.py
novana/valence.py
novana-0.3.0.dist-info/LICENSE
novana-0.3.0.dist-info/METADATA
novana-0.3.0.dist-info/WHEEL
novana-0.3.0.dist-info/top_level.txt
novana-0.3.0.dist-info/RECORD
