Metadata-Version: 2.1
Name: novana
Version: 0.3.0
Summary: NovAna (Novelty Analysis) is a cheminformatics tool that that extends the decomposition of molecules into Bemis-Murcko frameworks (J. Med. Chem. 1996, 39, 15, 2887-2893) and allows the enumeration of partially decomposed scaffolds.
Author: Gian Marco Ghiandoni
Author-email: ghiandoni.g@gmail.com
License: MIT
License-File: LICENSE
Requires-Dist: rdkit
